<launch4jConfig>
  <dontWrapJar>false</dontWrapJar>
  <headerType>gui</headerType>
  <jar>..\..\..\build\dist\liteloader-installer-1.6.4-01.jar</jar>
  <outfile>..\..\..\build\dist\liteloader-installer-1.6.4-01.exe</outfile>
  <errTitle></errTitle>
  <cmdLine></cmdLine>
  <chdir></chdir>
  <priority>normal</priority>
  <downloadUrl>http://java.com/download</downloadUrl>
  <supportUrl></supportUrl>
  <customProcName>false</customProcName>
  <stayAlive>false</stayAlive>
  <manifest>liteloader.manifest</manifest>
  <icon>..\liteloader_installer_icon.ico</icon>
  <jre>
    <path></path>
    <minVersion>1.6.0</minVersion>
    <maxVersion></maxVersion>
    <jdkPreference>preferJre</jdkPreference>
  </jre>
  <versionInfo>
    <fileVersion>1.6.4.1</fileVersion>
    <txtFileVersion>1.6.4-01</txtFileVersion>
    <fileDescription>LiteLoader Installer for Minecraft 1.6.4 release {ver.release}</fileDescription>
    <copyright>Copyright (C) 2013 Adam Mummery-Smith</copyright>
    <productVersion>1.6.4.1</productVersion>
    <txtProductVersion>1.6.4-01</txtProductVersion>
    <productName>LiteLoader</productName>
    <companyName></companyName>
    <internalName>LiteLoader</internalName>
    <originalFilename>liteloader-installer-1.6.4-01.exe</originalFilename>
  </versionInfo>
</launch4jConfig>